langgraph_viz/__init__.py
langgraph_viz/event_collector.py
langgraph_viz/serializer.py
langgraph_viz/server.py
langgraph_viz/state_tracker.py
langgraph_viz/wrapper.py
langgraph_viz/ui/index.html
langgraph_viz/ui/vite.svg
langgraph_viz/ui/assets/_baseUniq-3ezSaLub.js
langgraph_viz/ui/assets/arc-DSrHyIt-.js
langgraph_viz/ui/assets/architectureDiagram-VXUJARFQ-zUmIn2u6.js
langgraph_viz/ui/assets/blockDiagram-VD42YOAC-Dlp2q2IN.js
langgraph_viz/ui/assets/c4Diagram-YG6GDRKO-BXQdSKiZ.js
langgraph_viz/ui/assets/channel-Dbtb700R.js
langgraph_viz/ui/assets/chunk-4BX2VUAB-CTJn0yQI.js
langgraph_viz/ui/assets/chunk-55IACEB6-Bz85zQkZ.js
langgraph_viz/ui/assets/chunk-B4BG7PRW-CAJYtklL.js
langgraph_viz/ui/assets/chunk-DI55MBZ5-CyO-qujX.js
langgraph_viz/ui/assets/chunk-FMBD7UC4-CheWnEjx.js
langgraph_viz/ui/assets/chunk-QN33PNHL-Lyfxtd8u.js
langgraph_viz/ui/assets/chunk-QZHKN3VN-DribBUdn.js
langgraph_viz/ui/assets/chunk-TZMSLE5B-BgNrvudY.js
langgraph_viz/ui/assets/classDiagram-2ON5EDUG-hRssW2Fs.js
langgraph_viz/ui/assets/classDiagram-v2-WZHVMYZB-hRssW2Fs.js
langgraph_viz/ui/assets/clone-tUMRCiUo.js
langgraph_viz/ui/assets/cose-bilkent-S5V4N54A-CiJlxD-X.js
langgraph_viz/ui/assets/cytoscape.esm-5J0xJHOV.js
langgraph_viz/ui/assets/dagre-6UL2VRFP-crFHC2YI.js
langgraph_viz/ui/assets/defaultLocale-DNM2C9RQ.js
langgraph_viz/ui/assets/diagram-PSM6KHXK-nWZZRfrR.js
langgraph_viz/ui/assets/diagram-QEK2KX5R-C0GsHI6q.js
langgraph_viz/ui/assets/diagram-S2PKOQOG-CzN6fhHG.js
langgraph_viz/ui/assets/erDiagram-Q2GNP2WA-DUnv3Ot-.js
langgraph_viz/ui/assets/flowDiagram-NV44I4VS-bac5wEJK.js
langgraph_viz/ui/assets/ganttDiagram-JELNMOA3-CwoJejo4.js
langgraph_viz/ui/assets/gitGraphDiagram-NY62KEGX-BlrG9wBk.js
langgraph_viz/ui/assets/graph-D4QXXTPe.js
langgraph_viz/ui/assets/index-08x0p4Jj.js
langgraph_viz/ui/assets/index-lrmBaJjO.css
langgraph_viz/ui/assets/infoDiagram-WHAUD3N6-sR6-eWtg.js
langgraph_viz/ui/assets/init-Gi6I4Gst.js
langgraph_viz/ui/assets/journeyDiagram-XKPGCS4Q-D_xoNPlY.js
langgraph_viz-0.1.2.dist-info/METADATA
langgraph_viz-0.1.2.dist-info/WHEEL
langgraph_viz-0.1.2.dist-info/licenses/LICENSE
langgraph_viz-0.1.2.dist-info/RECORD
