Metadata-Version: 2.4
Name: langgraph-viz
Version: 0.1.2
Summary: Real-time browser-based visualization for LangGraph workflows
Project-URL: Homepage, https://github.com/mk-tdev/langgraph-viz
Project-URL: Repository, https://github.com/mk-tdev/langgraph-viz
Project-URL: Documentation, https://github.com/mk-tdev/langgraph-viz#readme
Project-URL: Bug Tracker, https://github.com/mk-tdev/langgraph-viz/issues
Author-email: MK T Dev <codewithmkdev@gmail.com>
License: MIT
License-File: LICENSE
Keywords: agents,debugging,langchain,langgraph,llm,state-machine,visualization,workflow
Classifier: Development Status :: 4 - Beta
Classifier: Intended Audience :: Developers
Classifier: License :: OSI Approved :: MIT License
Classifier: Programming Language :: Python :: 3
Classifier: Programming Language :: Python :: 3.9
Classifier: Programming Language :: Python :: 3.10
Classifier: Programming Language :: Python :: 3.11
Classifier: Programming Language :: Python :: 3.12
Classifier: Programming Language :: Python :: 3.13
Classifier: Topic :: Software Development :: Debuggers
Classifier: Topic :: Software Development :: Libraries :: Python Modules
Requires-Python: >=3.9
Requires-Dist: deepdiff>=6.7.0
Requires-Dist: fastapi>=0.104.0
Requires-Dist: langchain-anthropic>=0.3.22
Requires-Dist: langchain-openai>=0.3.35
Requires-Dist: langchain>=0.3.27
Requires-Dist: langgraph>=0.0.1
Requires-Dist: pydantic>=2.12.5
Requires-Dist: python-dotenv>=1.2.1
Requires-Dist: uvicorn[standard]>=0.24.0
Requires-Dist: websockets>=12.0
Provides-Extra: dev
Requires-Dist: black>=23.0.0; extra == 'dev'
Requires-Dist: pytest>=7.4.0; extra == 'dev'
Requires-Dist: ruff>=0.1.0; extra == 'dev'
